

[
  {
    "name": "Smart Watch",
    "description": "Fitness tracker smart watch with heart rate monitoring.",
    "category": "Wearables",
    "price": 99.99,
    "product_owner": "owner1@techdiscovery.com",
    "image_url": "https://cdn.pixabay.com/photo/2015/06/25/17/22/smart-watch-821559_1280.jpg",
    "upVotes": 23,
    "downVotes": 2,
    "tags": ["wearables", "fitness"],
    "externalLinks": "https://techdiscovery.com/smartwatch",
    "featured": true,  
    "created_at": "2023-01-05T11:22:10.158Z",
    "status": "accepted",
    "rating": 4.8
  },
  {
    "name": "Wireless Earbuds",
    "description": "Bluetooth earbuds with active noise cancellation.",
    "category": "Audio",
    "price": 149.99,
    "product_owner": "owner2@techdiscovery.com", 
    "image_url": "https://images.unsplash.com/photo-1590658006821-04f4008d5717?q=80&w=1632&auto=format&fit=crop&ixlib=rb-4.0.3&ixid=M3wxMjA3fDB8MHxwaG90by1wYWdlfHx8fGVufDB8fHx8fA%3D%3D",
    "upVotes": 19,
    "downVotes": 1,
    "tags": ["audio", "music"],
    "externalLinks": "https://techdiscovery.com/earbuds",
    "featured": false,
    "created_at": "2023-01-02T15:05:38.158Z",
    "status": "accepted",  
    "rating": 4.6
  },
  {
    "name": "Smart Bulb",
    "description": "Multicolor smart LED light bulb, voice and app controlled.",  
    "category": "Smart Home",
    "price": 39.99,
    "product_owner": "owner3@techdiscovery.com",
    "image_url": "https://images.unsplash.com/photo-1661254454741-94b4f0e6ebbb?q=80&w=1587&auto=format&fit=crop&ixlib=rb-4.0.3&ixid=M3wxMjA3fDB8MHxwaG90by1wYWdlfHx8fGVufDB8fHx8fA%3D%3D",
    "upVotes": 12,
    "downVotes": 3,
    "tags": ["lighting","smart home"],
    "externalLinks": "https://techdiscovery.com/smartbulb",
    "featured": false,
    "created_at": "2023-01-03T08:35:10.158Z",
    "status": "pending",
    "rating": 4  
  },
  {
    "name": "Fitness Tracker",
    "description": "Activity and sleep tracking fitness band.",
    "category": "Wearables", 
    "price": 49.99,
    "product_owner": "owner4@techdiscovery.com",
    "image_url": "https://plus.unsplash.com/premium_photo-1681433383783-661b519b154a?q=80&w=1460&auto=format&fit=crop&ixlib=rb-4.0.3&ixid=M3wxMjA3fDB8MHxwaG90by1wYWdlfHx8fGVufDB8fHx8fA%3D%3D",
    "upVotes": 16,
    "downVotes": 2,  
    "tags": ["fitness", "health"],
    "externalLinks": "https://techdiscovery.com/fitnesstracker",
    "featured": false,
    "created_at": "2023-01-04T18:22:38.158Z",
    "status": "pending",
    "rating": 4.1
  },
  {
    "name": "Wireless Keyboard",
    "description": "Slim Bluetooth keyboard for laptops and tablets.",
    "category": "Accessories", 
    "price": 29.99,
    "product_owner": "owner5@techdiscovery.com",
    "image_url": "https://images.unsplash.com/photo-1623875151988-83a83a375cd4?q=80&w=1632&auto=format&fit=crop&ixlib=rb-4.0.3&ixid=M3wxMjA3fDB8MHxwaG90by1wYWdlfHx8fGVufDB8fHx8fA%3D%3D", 
    "upVotes": 9,
    "downVotes": 1,
    "tags": ["productivity"],
    "externalLinks": "https://techdiscovery.com/keyboard",
    "featured": false, 
    "created_at": "2023-01-01T10:35:38.158Z",
    "status": "accepted",
    "rating": 4  
  },
  {
    "name": "Smart Display", 
    "description": "Voice assistant smart display for home control.",
    "category": "Smart Home",
    "price": 129.99,
    "product_owner": "owner6@techdiscovery.com",
    "image_url": "https://cdn.pixabay.com/photo/2018/01/17/09/43/iphone-3087842_1280.jpg",
    "upVotes": 19,
    "downVotes": 4,  
    "tags": ["display", "smart home"],
    "externalLinks": "https://techdiscovery.com/smartdisplay",
    "featured": true,
    "created_at": "2023-01-06T14:52:18.158Z",
    "status": "accepted",
    "rating": 4.3    
  },
  {
    "name": "Wireless Charger",
    "description": "Fast charging wireless phone charger.", 
    "category": "Accessories",
    "price": 25.99,
    "product_owner": "owner7@techdiscovery.com",
    "image_url": "https://cdn.pixabay.com/photo/2020/09/03/15/32/wireless-charger-5541662_1280.png",
    "upVotes": 14, 
    "downVotes": 2,
    "tags": ["charging"],
    "externalLinks": "https://techdiscovery.com/wirelesscharger",
    "featured": false,
    "created_at": "2022-12-29T09:35:10.158Z",
    "status": "accepted",
    "rating": 4.2
  },
  {
    "name": "Fitness Tracker",
    "description": "Activity and sleep tracking fitness band.",
    "category": "Wearables",
    "price": 49.99,
    "product_owner": "owner4@techdiscovery.com",
    "image_url": "https://cdn.pixabay.com/photo/2019/12/21/10/29/fitness-band-4710206_1280.jpg",    
    "upVotes": 16,
    "downVotes": 2,   
    "tags": ["fitness", "health"],
    "externalLinks": "https://techdiscovery.com/fitnesstracker",  
    "featured": false,
    "created_at": "2023-01-04T18:22:38.158Z",
    "status": "pending",
    "rating": 4.1
  },
  {
    "name": "VR Headset",
    "description": "Immersive virtual reality headset for gaming and entertainment.", 
    "category": "Gaming",
    "price": 399.99,
    "product_owner": "owner8@techdiscovery.com",
    "image_url": "https://cdn.pixabay.com/photo/2017/02/10/14/10/virtual-2055227_1280.png",
    "upVotes": 31,
    "downVotes": 5,  
    "tags": ["gaming", "vr"], 
    "externalLinks": "https://techdiscovery.com/vrheadset",
    "featured": true,  
    "created_at": "2023-01-05T08:02:18.158Z",
    "status": "accepted",
    "rating": 4.7   
  },
  {
    "name": "Smart Thermostat",
    "description": "Self-learning home thermostat to conserve energy.", 
    "category": "Smart Home",
    "price": 199.99,
    "product_owner": "owner9@techdiscovery.com",
    "image_url": "https://cdn.pixabay.com/photo/2017/01/24/18/26/smart-home-2006026_1280.png",
    "upVotes": 12,
    "downVotes": 2,   
    "tags": ["temperature","energy","smart home"],
    "externalLinks": "https://techdiscovery.com/thermostat",
    "featured": false,  
    "created_at": "2023-01-04T11:35:10.158Z",
    "status": "pending",
    "rating": 4.1
  },
  {
    "name": "Wireless Security Camera",
    "description": "Weatherproof outdoor WiFi security camera with night vision.",
    "category": "Smart Home",  
    "price": 89.99,
    "product_owner": "owner10@techdiscovery.com",
    "image_url": "https://cdn.pixabay.com/photo/2013/02/01/23/54/sweden-77216_1280.jpg", 
    "upVotes": 20,
    "downVotes": 3,  
    "tags": ["security", "outdoor"],
    "externalLinks": "https://techdiscovery.com/securitycam",
    "featured": false,
    "created_at": "2023-01-03T14:35:10.158Z",
    "status": "accepted",
    "rating": 4.6
  },
  {
    "name": "Smart Doorbell",
    "description": "WiFi video doorbell with motion detection alerts.", 
    "category": "Smart Home",
    "price": 149.99, 
    "product_owner": "owner11@techdiscovery.com",
    "image_url": "https://cdn.pixabay.com/photo/2014/02/28/11/55/bell-276831_1280.jpg",
    "upVotes": 13,
    "downVotes": 4,  
    "tags": ["security", "camera"],
    "externalLinks": "https://techdiscovery.com/doorbell", 
    "featured": false,
    "created_at": "2023-01-02T19:35:10.158Z",
    "status": "accepted",
    "rating": 4  
  },
  {
    "name": "eReader",
    "description": "High resolution digital ebook reader.",
    "category": "Electronics",
    "price": 129.99,
    "product_owner": "owner12@techdiscovery.com",
    "image_url": "https://cdn.pixabay.com/photo/2016/02/02/20/42/reading-1176073_1280.jpg",
    "upVotes": 10, 
    "downVotes": 2,
    "tags": ["books","reading"], 
    "externalLinks": "https://techdiscovery.com/ereader",
    "featured": false, 
    "created_at": "2022-12-31T11:35:10.158Z",
    "status": "accepted",
    "rating": 4.3
  },
  {
    "name": "Smart Plug", 
    "description": "Voice and app controlled wifi smart plug.",
    "category": "Smart Home",
    "price": 24.99,
    "product_owner": "owner13@techdiscovery.com",  
    "image_url": "https://cdn.pixabay.com/photo/2018/01/24/17/33/light-bulb-3104355_1280.jpg",
    "upVotes": 8,
    "downVotes": 3, 
    "tags": ["smart home","energy"],
    "externalLinks": "https://techdiscovery.com/smartplug",  
    "featured": false,
    "created_at": "2023-01-01T16:35:10.158Z", 
    "status": "pending",
    "rating": 3.9
  },
  { 
    "name": "Smart Speaker",
    "description": "Voice assistant wifi speaker for music and home automation.",  
    "category": "Audio",
    "price": 99.99,
    "product_owner": "owner14techdiscovery.com",
    "image_url": "https://cdn.pixabay.com/photo/2021/01/09/12/30/speaker-5902204_1280.jpg", 
    "upVotes": 29,
    "downVotes": 2,
    "tags": ["audio", "smart home"],
    "externalLinks": "https://techdiscovery.com/smartspeaker",   
    "featured": true, 
    "created_at": "2022-12-29T13:45:10.158Z",
    "status": "accepted", 
    "rating": 4.7
  },
  {
    "name": "Smart Light",
    "description": "Customizable smart LED light panels.",
    "category": "Smart Home", 
    "price": 79.99,
    "product_owner": "owner15@techdiscovery.com",
    "image_url": "https://cdn.pixabay.com/photo/2021/02/10/12/36/hue-6001935_1280.jpg",
    "upVotes": 17,
    "downVotes": 1,   
    "tags": ["lighting", "decor"],
    "externalLinks": "https://techdiscovery.com/smartlight", 
    "featured": false,
    "created_at": "2023-01-03T18:35:10.158Z", 
    "status": "accepted",
    "rating": 4.3  
  },
  {
    "name": "Smart Sprinkler", 
    "description": "App and voice controlled automated sprinkler system.",
    "category": "Smart Home",  
    "price": 149.99, 
    "product_owner": "owner16@techdiscovery.com",
    "image_url": "https://cdn.pixabay.com/photo/2017/08/30/08/34/robot-mower-2696318_1280.jpg",
    "upVotes": 4,
    "downVotes": 1,   
    "tags": ["garden", "landscaping"],
    "externalLinks": "https://techdiscovery.com/sprinkler",
    "featured": false,
    "created_at": "2023-01-04T08:35:10.158Z",
    "status": "pending",
    "rating": 3.8
  }  
]